userdb/__init__.py
userdb-1.1.3.dist-info/METADATA
userdb-1.1.3.dist-info/WHEEL
userdb-1.1.3.dist-info/top_level.txt
userdb-1.1.3.dist-info/RECORD
